<annotation>
	<folder>Images</folder>
	<filename>dataprep674.jpeg</filename>
	<path>/Users/arunprakash/Documents/L&amp;D/Tensorflow/annotations/cleandoc/Images/dataprep674.jpeg</path>
	<source>
		<database>Unknown</database>
	</source>
	<size>
		<width>1656</width>
		<height>2339</height>
		<depth>3</depth>
	</size>
	<segmented>0</segmented>
	<object>
		<name>seal</name>
		<pose>Unspecified</pose>
		<truncated>0</truncated>
		<difficult>0</difficult>
		<bndbox>
			<xmin>145</xmin>
			<ymin>261</ymin>
			<xmax>422</xmax>
			<ymax>507</ymax>
		</bndbox>
	</object>
	<object>
		<name>seal</name>
		<pose>Unspecified</pose>
		<truncated>0</truncated>
		<difficult>0</difficult>
		<bndbox>
			<xmin>456</xmin>
			<ymin>201</ymin>
			<xmax>756</xmax>
			<ymax>509</ymax>
		</bndbox>
	</object>
	<object>
		<name>noise</name>
		<pose>Unspecified</pose>
		<truncated>1</truncated>
		<difficult>0</difficult>
		<bndbox>
			<xmin>1605</xmin>
			<ymin>1</ymin>
			<xmax>1650</xmax>
			<ymax>2327</ymax>
		</bndbox>
	</object>
	<object>
		<name>pageno</name>
		<pose>Unspecified</pose>
		<truncated>0</truncated>
		<difficult>0</difficult>
		<bndbox>
			<xmin>782</xmin>
			<ymin>2078</ymin>
			<xmax>896</xmax>
			<ymax>2175</ymax>
		</bndbox>
	</object>
</annotation>
