<annotation>
	<folder>Images</folder>
	<filename>dataprep612.jpeg</filename>
	<path>/Users/arunprakash/Documents/L&amp;D/Tensorflow/annotations/cleandoc/Images/dataprep612.jpeg</path>
	<source>
		<database>Unknown</database>
	</source>
	<size>
		<width>1653</width>
		<height>2339</height>
		<depth>1</depth>
	</size>
	<segmented>0</segmented>
	<object>
		<name>pageno</name>
		<pose>Unspecified</pose>
		<truncated>0</truncated>
		<difficult>0</difficult>
		<bndbox>
			<xmin>748</xmin>
			<ymin>2152</ymin>
			<xmax>914</xmax>
			<ymax>2264</ymax>
		</bndbox>
	</object>
	<object>
		<name>pageno</name>
		<pose>Unspecified</pose>
		<truncated>0</truncated>
		<difficult>0</difficult>
		<bndbox>
			<xmin>894</xmin>
			<ymin>2158</ymin>
			<xmax>1028</xmax>
			<ymax>2278</ymax>
		</bndbox>
	</object>
	<object>
		<name>tag</name>
		<pose>Unspecified</pose>
		<truncated>0</truncated>
		<difficult>0</difficult>
		<bndbox>
			<xmin>114</xmin>
			<ymin>2161</ymin>
			<xmax>506</xmax>
			<ymax>2221</ymax>
		</bndbox>
	</object>
	<object>
		<name>seal</name>
		<pose>Unspecified</pose>
		<truncated>0</truncated>
		<difficult>0</difficult>
		<bndbox>
			<xmin>1354</xmin>
			<ymin>2024</ymin>
			<xmax>1588</xmax>
			<ymax>2232</ymax>
		</bndbox>
	</object>
	<object>
		<name>tag</name>
		<pose>Unspecified</pose>
		<truncated>0</truncated>
		<difficult>0</difficult>
		<bndbox>
			<xmin>1234</xmin>
			<ymin>2178</ymin>
			<xmax>1488</xmax>
			<ymax>2215</ymax>
		</bndbox>
	</object>
	<object>
		<name>seal</name>
		<pose>Unspecified</pose>
		<truncated>0</truncated>
		<difficult>0</difficult>
		<bndbox>
			<xmin>426</xmin>
			<ymin>92</ymin>
			<xmax>740</xmax>
			<ymax>389</ymax>
		</bndbox>
	</object>
</annotation>
