<annotation>
	<folder>Images</folder>
	<filename>dataprep587.jpeg</filename>
	<path>/Users/arunprakash/Documents/L&amp;D/Tensorflow/annotations/cleandoc/Images/dataprep587.jpeg</path>
	<source>
		<database>Unknown</database>
	</source>
	<size>
		<width>1654</width>
		<height>2338</height>
		<depth>3</depth>
	</size>
	<segmented>0</segmented>
	<object>
		<name>noise</name>
		<pose>Unspecified</pose>
		<truncated>0</truncated>
		<difficult>0</difficult>
		<bndbox>
			<xmin>41</xmin>
			<ymin>494</ymin>
			<xmax>147</xmax>
			<ymax>2040</ymax>
		</bndbox>
	</object>
	<object>
		<name>noise</name>
		<pose>Unspecified</pose>
		<truncated>0</truncated>
		<difficult>0</difficult>
		<bndbox>
			<xmin>1544</xmin>
			<ymin>1700</ymin>
			<xmax>1587</xmax>
			<ymax>2291</ymax>
		</bndbox>
	</object>
	<object>
		<name>tag</name>
		<pose>Unspecified</pose>
		<truncated>0</truncated>
		<difficult>0</difficult>
		<bndbox>
			<xmin>1052</xmin>
			<ymin>2057</ymin>
			<xmax>1389</xmax>
			<ymax>2168</ymax>
		</bndbox>
	</object>
	<object>
		<name>tag</name>
		<pose>Unspecified</pose>
		<truncated>0</truncated>
		<difficult>0</difficult>
		<bndbox>
			<xmin>1175</xmin>
			<ymin>37</ymin>
			<xmax>1595</xmax>
			<ymax>151</ymax>
		</bndbox>
	</object>
	<object>
		<name>seal</name>
		<pose>Unspecified</pose>
		<truncated>0</truncated>
		<difficult>0</difficult>
		<bndbox>
			<xmin>1149</xmin>
			<ymin>220</ymin>
			<xmax>1481</xmax>
			<ymax>540</ymax>
		</bndbox>
	</object>
	<object>
		<name>seal</name>
		<pose>Unspecified</pose>
		<truncated>0</truncated>
		<difficult>0</difficult>
		<bndbox>
			<xmin>598</xmin>
			<ymin>17</ymin>
			<xmax>1041</xmax>
			<ymax>308</ymax>
		</bndbox>
	</object>
	<object>
		<name>seal</name>
		<pose>Unspecified</pose>
		<truncated>0</truncated>
		<difficult>0</difficult>
		<bndbox>
			<xmin>218</xmin>
			<ymin>43</ymin>
			<xmax>501</xmax>
			<ymax>331</ymax>
		</bndbox>
	</object>
</annotation>
