<annotation>
	<folder>Images</folder>
	<filename>dataprep398.jpeg</filename>
	<path>/Users/arunprakash/Documents/L&amp;D/Tensorflow/annotations/cleandoc/Images/dataprep398.jpeg</path>
	<source>
		<database>Unknown</database>
	</source>
	<size>
		<width>1654</width>
		<height>2338</height>
		<depth>3</depth>
	</size>
	<segmented>0</segmented>
	<object>
		<name>seal</name>
		<pose>Unspecified</pose>
		<truncated>0</truncated>
		<difficult>0</difficult>
		<bndbox>
			<xmin>152</xmin>
			<ymin>200</ymin>
			<xmax>401</xmax>
			<ymax>457</ymax>
		</bndbox>
	</object>
	<object>
		<name>seal</name>
		<pose>Unspecified</pose>
		<truncated>0</truncated>
		<difficult>0</difficult>
		<bndbox>
			<xmin>352</xmin>
			<ymin>177</ymin>
			<xmax>621</xmax>
			<ymax>463</ymax>
		</bndbox>
	</object>
	<object>
		<name>seal</name>
		<pose>Unspecified</pose>
		<truncated>0</truncated>
		<difficult>0</difficult>
		<bndbox>
			<xmin>367</xmin>
			<ymin>657</ymin>
			<xmax>538</xmax>
			<ymax>791</ymax>
		</bndbox>
	</object>
	<object>
		<name>tag</name>
		<pose>Unspecified</pose>
		<truncated>0</truncated>
		<difficult>0</difficult>
		<bndbox>
			<xmin>109</xmin>
			<ymin>2123</ymin>
			<xmax>561</xmax>
			<ymax>2243</ymax>
		</bndbox>
	</object>
	<object>
		<name>tag</name>
		<pose>Unspecified</pose>
		<truncated>0</truncated>
		<difficult>0</difficult>
		<bndbox>
			<xmin>1121</xmin>
			<ymin>2148</ymin>
			<xmax>1509</xmax>
			<ymax>2266</ymax>
		</bndbox>
	</object>
	<object>
		<name>noise</name>
		<pose>Unspecified</pose>
		<truncated>0</truncated>
		<difficult>0</difficult>
		<bndbox>
			<xmin>1518</xmin>
			<ymin>1240</ymin>
			<xmax>1589</xmax>
			<ymax>2277</ymax>
		</bndbox>
	</object>
	<object>
		<name>noise</name>
		<pose>Unspecified</pose>
		<truncated>0</truncated>
		<difficult>0</difficult>
		<bndbox>
			<xmin>1444</xmin>
			<ymin>483</ymin>
			<xmax>1529</xmax>
			<ymax>1086</ymax>
		</bndbox>
	</object>
</annotation>
