<annotation>
	<folder>Images</folder>
	<filename>dataprep161.jpeg</filename>
	<path>/Users/arunprakash/Documents/L&amp;D/Tensorflow/annotations/new strategy/Images/dataprep161.jpeg</path>
	<source>
		<database>Unknown</database>
	</source>
	<size>
		<width>1653</width>
		<height>2337</height>
		<depth>1</depth>
	</size>
	<segmented>0</segmented>
	<object>
		<name>pageno</name>
		<pose>Unspecified</pose>
		<truncated>0</truncated>
		<difficult>0</difficult>
		<bndbox>
			<xmin>468</xmin>
			<ymin>2048</ymin>
			<xmax>640</xmax>
			<ymax>2166</ymax>
		</bndbox>
	</object>
</annotation>
