<annotation>
	<folder>Images</folder>
	<filename>dataprep209.jpeg</filename>
	<path>/Users/arunprakash/Documents/L&amp;D/Tensorflow/annotations/cleandoc/Images/dataprep209.jpeg</path>
	<source>
		<database>Unknown</database>
	</source>
	<size>
		<width>1654</width>
		<height>2340</height>
		<depth>1</depth>
	</size>
	<segmented>0</segmented>
	<object>
		<name>seal</name>
		<pose>Unspecified</pose>
		<truncated>0</truncated>
		<difficult>0</difficult>
		<bndbox>
			<xmin>35</xmin>
			<ymin>81</ymin>
			<xmax>367</xmax>
			<ymax>364</ymax>
		</bndbox>
	</object>
	<object>
		<name>seal</name>
		<pose>Unspecified</pose>
		<truncated>0</truncated>
		<difficult>0</difficult>
		<bndbox>
			<xmin>32</xmin>
			<ymin>752</ymin>
			<xmax>372</xmax>
			<ymax>1069</ymax>
		</bndbox>
	</object>
	<object>
		<name>seal</name>
		<pose>Unspecified</pose>
		<truncated>0</truncated>
		<difficult>0</difficult>
		<bndbox>
			<xmin>118</xmin>
			<ymin>1238</ymin>
			<xmax>384</xmax>
			<ymax>1504</ymax>
		</bndbox>
	</object>
	<object>
		<name>seal</name>
		<pose>Unspecified</pose>
		<truncated>0</truncated>
		<difficult>0</difficult>
		<bndbox>
			<xmin>918</xmin>
			<ymin>98</ymin>
			<xmax>1375</xmax>
			<ymax>392</ymax>
		</bndbox>
	</object>
	<object>
		<name>seal</name>
		<pose>Unspecified</pose>
		<truncated>0</truncated>
		<difficult>0</difficult>
		<bndbox>
			<xmin>524</xmin>
			<ymin>435</ymin>
			<xmax>1009</xmax>
			<ymax>578</ymax>
		</bndbox>
	</object>
	<object>
		<name>tag</name>
		<pose>Unspecified</pose>
		<truncated>0</truncated>
		<difficult>0</difficult>
		<bndbox>
			<xmin>61</xmin>
			<ymin>2221</ymin>
			<xmax>429</xmax>
			<ymax>2324</ymax>
		</bndbox>
	</object>
</annotation>
