<annotation>
	<folder>Images</folder>
	<filename>termbatch19.jpeg</filename>
	<path>/Users/arunprakash/Documents/L&amp;D/Tensorflow/darkflow/train/Images/termbatch19.jpeg</path>
	<source>
		<database>Unknown</database>
	</source>
	<size>
		<width>1653</width>
		<height>2339</height>
		<depth>3</depth>
	</size>
	<segmented>0</segmented>
	<object>
		<name>tag</name>
		<pose>Unspecified</pose>
		<truncated>1</truncated>
		<difficult>0</difficult>
		<bndbox>
			<xmin>1</xmin>
			<ymin>198</ymin>
			<xmax>308</xmax>
			<ymax>309</ymax>
		</bndbox>
	</object>
	<object>
		<name>seal</name>
		<pose>Unspecified</pose>
		<truncated>0</truncated>
		<difficult>0</difficult>
		<bndbox>
			<xmin>254</xmin>
			<ymin>27</ymin>
			<xmax>546</xmax>
			<ymax>401</ymax>
		</bndbox>
	</object>
	<object>
		<name>seal</name>
		<pose>Unspecified</pose>
		<truncated>0</truncated>
		<difficult>0</difficult>
		<bndbox>
			<xmin>506</xmin>
			<ymin>15</ymin>
			<xmax>783</xmax>
			<ymax>338</ymax>
		</bndbox>
	</object>
	<object>
		<name>seal</name>
		<pose>Unspecified</pose>
		<truncated>0</truncated>
		<difficult>0</difficult>
		<bndbox>
			<xmin>754</xmin>
			<ymin>49</ymin>
			<xmax>1083</xmax>
			<ymax>361</ymax>
		</bndbox>
	</object>
	<object>
		<name>tag</name>
		<pose>Unspecified</pose>
		<truncated>0</truncated>
		<difficult>0</difficult>
		<bndbox>
			<xmin>1117</xmin>
			<ymin>69</ymin>
			<xmax>1617</xmax>
			<ymax>201</ymax>
		</bndbox>
	</object>
	<object>
		<name>tag</name>
		<pose>Unspecified</pose>
		<truncated>0</truncated>
		<difficult>0</difficult>
		<bndbox>
			<xmin>1263</xmin>
			<ymin>507</ymin>
			<xmax>1560</xmax>
			<ymax>572</ymax>
		</bndbox>
	</object>
	<object>
		<name>noise</name>
		<pose>Unspecified</pose>
		<truncated>0</truncated>
		<difficult>0</difficult>
		<bndbox>
			<xmin>320</xmin>
			<ymin>1804</ymin>
			<xmax>491</xmax>
			<ymax>2187</ymax>
		</bndbox>
	</object>
	<object>
		<name>pageno</name>
		<pose>Unspecified</pose>
		<truncated>0</truncated>
		<difficult>0</difficult>
		<bndbox>
			<xmin>828</xmin>
			<ymin>2175</ymin>
			<xmax>960</xmax>
			<ymax>2278</ymax>
		</bndbox>
	</object>
	<object>
		<name>text</name>
		<pose>Unspecified</pose>
		<truncated>0</truncated>
		<difficult>0</difficult>
		<bndbox>
			<xmin>237</xmin>
			<ymin>558</ymin>
			<xmax>1571</xmax>
			<ymax>1821</ymax>
		</bndbox>
	</object>
</annotation>
